css_classes/__init__.py
css_classes/css_classes.py
css_classes-1.1.dist-info/DESCRIPTION.rst
css_classes-1.1.dist-info/METADATA
css_classes-1.1.dist-info/RECORD
css_classes-1.1.dist-info/WHEEL
css_classes-1.1.dist-info/metadata.json
css_classes-1.1.dist-info/top_level.txt
